odoo/addons/bi_view_report/__init__.py
odoo/addons/bi_view_report/__manifest__.py
odoo/addons/bi_view_report/reports/bi_view_report_email_template.xml
odoo/addons/bi_view_report/wizards/__init__.py
odoo/addons/bi_view_report/wizards/bi_view_report_wizard.py
odoo/addons/bi_view_report/wizards/bi_view_report_wizard.xml
odoo12_addon_bi_view_report-12.0.1.0.0.99.dev5.dist-info/METADATA
odoo12_addon_bi_view_report-12.0.1.0.0.99.dev5.dist-info/WHEEL
odoo12_addon_bi_view_report-12.0.1.0.0.99.dev5.dist-info/top_level.txt
odoo12_addon_bi_view_report-12.0.1.0.0.99.dev5.dist-info/RECORD
